{"trial_id": "17", "hyperparameters": {"space": [{"class_name": "Int", "config": {"name": "input_units", "default": null, "conditions": [], "min_value": 128, "max_value": 512, "step": 64, "sampling": "linear"}}, {"class_name": "Float", "config": {"name": "l2_input", "default": 0.0001, "conditions": [], "min_value": 0.0001, "max_value": 0.01, "step": null, "sampling": "log"}}, {"class_name": "Float", "config": {"name": "dropout_input", "default": 0.3, "conditions": [], "min_value": 0.3, "max_value": 0.6, "step": 0.1, "sampling": "linear"}}, {"class_name": "Int", "config": {"name": "n_layers", "default": null, "conditions": [], "min_value": 2, "max_value": 5, "step": 1, "sampling": "linear"}}, {"class_name": "Int", "config": {"name": "units_0", "default": null, "conditions": [], "min_value": 32, "max_value": 256, "step": 32, "sampling": "linear"}}, {"class_name": "Choice", "config": {"name": "activation_0", "default": "relu", "conditions": [], "values": ["relu", "elu", "swish"], "ordered": false}}, {"class_name": "Float", "config": {"name": "l2_0", "default": 0.0001, "conditions": [], "min_value": 0.0001, "max_value": 0.01, "step": null, "sampling": "log"}}, {"class_name": "Boolean", "config": {"name": "batch_norm_0", "default": false, "conditions": []}}, {"class_name": "Float", "config": {"name": "dropout_0", "default": 0.2, "conditions": [], "min_value": 0.2, "max_value": 0.5, "step": 0.1, "sampling": "linear"}}, {"class_name": "Int", "config": {"name": "units_1", "default": null, "conditions": [], "min_value": 32, "max_value": 256, "step": 32, "sampling": "linear"}}, {"class_name": "Choice", "config": {"name": "activation_1", "default": "relu", "conditions": [], "values": ["relu", "elu", "swish"], "ordered": false}}, {"class_name": "Float", "config": {"name": "l2_1", "default": 0.0001, "conditions": [], "min_value": 0.0001, "max_value": 0.01, "step": null, "sampling": "log"}}, {"class_name": "Boolean", "config": {"name": "batch_norm_1", "default": false, "conditions": []}}, {"class_name": "Float", "config": {"name": "dropout_1", "default": 0.2, "conditions": [], "min_value": 0.2, "max_value": 0.5, "step": 0.1, "sampling": "linear"}}, {"class_name": "Boolean", "config": {"name": "attention_layer", "default": false, "conditions": []}}, {"class_name": "Float", "config": {"name": "learning_rate", "default": 0.0001, "conditions": [], "min_value": 0.0001, "max_value": 0.01, "step": null, "sampling": "log"}}, {"class_name": "Int", "config": {"name": "units_2", "default": null, "conditions": [], "min_value": 32, "max_value": 256, "step": 32, "sampling": "linear"}}, {"class_name": "Choice", "config": {"name": "activation_2", "default": "relu", "conditions": [], "values": ["relu", "elu", "swish"], "ordered": false}}, {"class_name": "Float", "config": {"name": "l2_2", "default": 0.0001, "conditions": [], "min_value": 0.0001, "max_value": 0.01, "step": null, "sampling": "log"}}, {"class_name": "Boolean", "config": {"name": "batch_norm_2", "default": false, "conditions": []}}, {"class_name": "Float", "config": {"name": "dropout_2", "default": 0.2, "conditions": [], "min_value": 0.2, "max_value": 0.5, "step": 0.1, "sampling": "linear"}}, {"class_name": "Int", "config": {"name": "units_3", "default": null, "conditions": [], "min_value": 32, "max_value": 256, "step": 32, "sampling": "linear"}}, {"class_name": "Choice", "config": {"name": "activation_3", "default": "relu", "conditions": [], "values": ["relu", "elu", "swish"], "ordered": false}}, {"class_name": "Float", "config": {"name": "l2_3", "default": 0.0001, "conditions": [], "min_value": 0.0001, "max_value": 0.01, "step": null, "sampling": "log"}}, {"class_name": "Boolean", "config": {"name": "batch_norm_3", "default": false, "conditions": []}}, {"class_name": "Float", "config": {"name": "dropout_3", "default": 0.2, "conditions": [], "min_value": 0.2, "max_value": 0.5, "step": 0.1, "sampling": "linear"}}, {"class_name": "Int", "config": {"name": "attention_units", "default": null, "conditions": [], "min_value": 16, "max_value": 64, "step": 16, "sampling": "linear"}}], "values": {"input_units": 192, "l2_input": 0.0008487740493780784, "dropout_input": 0.4, "n_layers": 3, "units_0": 192, "activation_0": "swish", "l2_0": 0.0004917594603315001, "batch_norm_0": false, "dropout_0": 0.30000000000000004, "units_1": 96, "activation_1": "relu", "l2_1": 0.006884360850715642, "batch_norm_1": false, "dropout_1": 0.30000000000000004, "attention_layer": true, "learning_rate": 0.0036179319024039567, "units_2": 160, "activation_2": "relu", "l2_2": 0.00014426570914461573, "batch_norm_2": false, "dropout_2": 0.30000000000000004, "units_3": 224, "activation_3": "relu", "l2_3": 0.002143675732751604, "batch_norm_3": true, "dropout_3": 0.30000000000000004, "attention_units": 48}}, "metrics": {"metrics": {"accuracy": {"direction": "max", "observations": [{"value": [0.8790373802185059], "step": 21}]}, "auc": {"direction": "max", "observations": [{"value": [0.9558895826339722], "step": 21}]}, "loss": {"direction": "min", "observations": [{"value": [0.9908801317214966], "step": 21}]}, "precision": {"direction": "max", "observations": [{"value": [0.8136125802993774], "step": 21}]}, "recall": {"direction": "max", "observations": [{"value": [0.9835442900657654], "step": 21}]}, "val_accuracy": {"direction": "max", "observations": [{"value": [0.7240506410598755], "step": 21}]}, "val_auc": {"direction": "max", "observations": [{"value": [0.6755499243736267], "step": 21}]}, "val_loss": {"direction": "min", "observations": [{"value": [2.9891357421875], "step": 21}]}, "val_precision": {"direction": "max", "observations": [{"value": [0.7834395170211792], "step": 21}]}, "val_recall": {"direction": "max", "observations": [{"value": [0.6212121248245239], "step": 21}]}, "learning_rate": {"direction": "min", "observations": [{"value": [0.0009044829639606178], "step": 21}]}}}, "score": 0.7834395170211792, "best_step": 21, "status": "COMPLETED", "message": null}